[
    {
        "model": "auth.user",
        "pk": -1,
        "fields": {
            "password": "pbkdf2_sha256$260000$zgDLsIfSRi0Qeq155JU2E8$01A7og6ptAYNDTVDU4cS+O618bs29eDcH9+eh1ZVbuU=",
            "last_login": null,
            "is_superuser": true,
            "username": "admin",
            "first_name": "",
            "last_name": "",
            "email": "admin@admin.com",
            "is_staff": true,
            "is_active": true,
            "date_joined": "2023-02-03T01:58:17.376Z",
            "groups": [],
            "user_permissions": []
        }
    },
    {
        "model": "auth.user",
        "pk": -2,
        "fields": {
            "password": "pbkdf2_sha256$260000$CeNDFlIZvkj3JGPqC88Nam$1vhb6/GolMteeEDv9xby6HKkslepxfjxCFN2m6dU7rw=",
            "last_login": "2023-02-03T01:59:51.659Z",
            "is_superuser": true,
            "username": "jaime",
            "first_name": "",
            "last_name": "",
            "email": "admin@admin.com",
            "is_staff": true,
            "is_active": true,
            "date_joined": "2023-02-03T01:58:17.565Z",
            "groups": [],
            "user_permissions": []
        }
    },
    {
        "model": "management.denomination",
        "pk": 1,
        "fields": {
            "value": "20000",
            "name": null,
            "currency": "CLP",
            "type": "Bill",
            "displayOrder": 1
        }
    },
    {
        "model": "management.denomination",
        "pk": 2,
        "fields": {
            "value": "10000",
            "name": null,
            "currency": "CLP",
            "type": "Bill",
            "displayOrder": 2
        }
    },
    {
        "model": "management.denomination",
        "pk": 3,
        "fields": {
            "value": "5000",
            "name": null,
            "currency": "CLP",
            "type": "Bill",
            "displayOrder": 3
        }
    },
    {
        "model": "management.denomination",
        "pk": 4,
        "fields": {
            "value": "2000",
            "name": null,
            "currency": "CLP",
            "type": "Bill",
            "displayOrder": 4
        }
    },
    {
        "model": "management.denomination",
        "pk": 5,
        "fields": {
            "value": "1000",
            "name": null,
            "currency": "CLP",
            "type": "Bill",
            "displayOrder": 5
        }
    },
    {
        "model": "management.denomination",
        "pk": 6,
        "fields": {
            "value": "500",
            "name": null,
            "currency": "CLP",
            "type": "Coin",
            "displayOrder": 1
        }
    },
    {
        "model": "management.denomination",
        "pk": 7,
        "fields": {
            "value": "100",
            "name": null,
            "currency": "CLP",
            "type": "Coin",
            "displayOrder": 2
        }
    },
    {
        "model": "management.denomination",
        "pk": 8,
        "fields": {
            "value": "50",
            "name": null,
            "currency": "CLP",
            "type": "Coin",
            "displayOrder": 3
        }
    },
    {
        "model": "management.denomination",
        "pk": 9,
        "fields": {
            "value": "10",
            "name": null,
            "currency": "CLP",
            "type": "Coin",
            "displayOrder": 4
        }
    },
    {
        "model": "management.company",
        "pk": -1,
        "fields": {
            "name": "la asaderia",
            "address": ".",
            "manager": -2
        }
    }
]